{
  "article_id": 229,
  "article_title": "Tội vi phạm các quy định về quản lý đất đai",
  "error_type": "ValueError",
  "error_message": "Không trích xuất được sau 3 lần. Lỗi cuối: Không tìm thấy JSON hợp lệ trong phản hồi của model. Preview: {   \"rules\": [     {       \"legal_subject\": \"Người nào lợi dụng hoặc lạm dụng chức vụ, quyền hạn\",       \"condition\": \"giao đất, thu hồi, cho thuê, cho phép chuyển quyền sử dụng, cho phép chuyển mục đích sử dụng đất trái quy định của pháp luật thuộc một trong các trường hợp a, b, c\",       \"effect\": \"bị phạt cải tạo không giam giữ đến 03 năm hoặc phạt tù từ 06 tháng đến 03 năm\",       \"rule_text\": \"Nếu một người lợi dụng hoặc lạm dụng chức vụ, quyền hạn giao đất, thu hồi, cho thuê, cho phép chuyển quyền sử dụng, cho phép chuyển mục đích sử dụng đất trái quy định của pháp luật thuộc một trong các trường hợp a, b, c thì người đó bị phạt cải tạo không giam giữ đến 03 năm hoặc phạt tù từ 06 tháng đến 03 năm.\"     },     {       \"legal_subject\": \"Người phạm tội\",       \"condition\": \"phạm tội th. Parse errors: whole_response=Unterminated string starting at: line 241 column 20 (char 13404)",
  "raw_response_file": "data/2_blhs_rules_raw_errors/article_229_response.txt"
}